leetstalker/__init__.py
leetstalker/leetstalker.py
leetstalker-1.0.1.dist-info/LICENSE
leetstalker-1.0.1.dist-info/METADATA
leetstalker-1.0.1.dist-info/WHEEL
leetstalker-1.0.1.dist-info/entry_points.txt
leetstalker-1.0.1.dist-info/top_level.txt
leetstalker-1.0.1.dist-info/RECORD
