Metadata-Version: 2.1
Name: leetstalker
Version: 1.0.1
Summary: Fetch user stats from leetcode
Author-email: Varun Sudheer Nair <nairvarun104@gmail.com>
Maintainer-email: Varun Sudheer Nair <nairvarun104@gmail.com>
License: MIT License
Project-URL: Repository, https://github.com/nairvarun/leetstalker.git
Project-URL: Issues, https://github.com/nairvarun/leetstalker/issues
Project-URL: Changelog, https://github.com/nairvarun/leetstalker/blob/main/CHANGELOG.md
Requires-Python: >=3.11
License-File: LICENSE
Requires-Dist: aiohttp
Requires-Dist: rich
